google_flights/__init__.py
google_flights/decoder.py
google_flights/filter.py
google_flights/flights.proto
google_flights/flights_pb2.py
google_flights/flights_pb_implem.py
google_flights/local_playwright.py
google_flights/main.py
google_flights/search.py
google_flights/test.py
google_flights-0.0.7.dist-info/METADATA
google_flights-0.0.7.dist-info/WHEEL
google_flights-0.0.7.dist-info/licenses/LICENSE
google_flights-0.0.7.dist-info/RECORD
