Metadata-Version: 2.4
Name: google-flights
Version: 0.0.7
Summary: Google Flights scraper (API) implemented in Python
Project-URL: Homepage, https://github.com/hexus07/google_flight_scraper
Project-URL: Issues, https://github.com/hexus07/google_flight_scraper/issues
Author-email: Daniil <daniilchuhai07@gmail.com>
License-Expression: MIT
License-File: LICENSE
Keywords: airport,flights,google,google-flights,js,passengers,protobuf,scraper,travel,trip
Classifier: License :: OSI Approved :: MIT License
Classifier: Operating System :: OS Independent
Classifier: Programming Language :: Python :: 3
Requires-Python: >=3.8
Requires-Dist: primp
Requires-Dist: protobuf
Requires-Dist: requests
Requires-Dist: selectolax
Requires-Dist: typing-extensions
Provides-Extra: local
Requires-Dist: playwright; extra == 'local'
